{"trial_id": "3", "hyperparameters": {"space": [{"class_name": "Choice", "config": {"name": "optimizer", "default": "Adam", "conditions": [], "values": ["Adam", "sgd", "rmsprop", "adagrad", "adadelta", "nag"], "ordered": false}}], "values": {"optimizer": "sgd"}}, "metrics": {"metrics": {"accuracy": {"direction": "max", "observations": [{"value": [0.6921824216842651], "step": 4}]}, "loss": {"direction": "min", "observations": [{"value": [0.6157733798027039], "step": 4}]}, "val_accuracy": {"direction": "max", "observations": [{"value": [0.7402597665786743], "step": 4}]}, "val_loss": {"direction": "min", "observations": [{"value": [0.5677282214164734], "step": 4}]}}}, "score": 0.7402597665786743, "best_step": 4, "status": "COMPLETED", "message": null}