{"ongoing_trials": {}, "hyperparameters": {"space": [{"class_name": "Int", "config": {"name": "num_layer", "default": null, "conditions": [], "min_value": 1, "max_value": 10, "step": 1, "sampling": "linear"}}], "values": {"num_layer": 1}}, "start_order": ["0", "1", "2"], "end_order": ["0", "1", "2"], "run_times": {"0": 1, "1": 1, "2": 1}, "retry_queue": [], "seed": 5184, "seed_state": 5187, "tried_so_far": ["46e8110ddea3a0ce3c879d46c0a82a54", "7ee071243f5c5439ebaf2563ecb45525", "6f57a12af823906d4f08e82fd9f6eebd"], "id_to_hash": {"0": "7ee071243f5c5439ebaf2563ecb45525", "1": "6f57a12af823906d4f08e82fd9f6eebd", "2": "46e8110ddea3a0ce3c879d46c0a82a54"}, "display": {"search_start": "2025-12-24T14:45:09.556922", "trial_start": {"0": "2025-12-24T14:45:09.556922", "1": "2025-12-24T14:45:12.087047", "2": "2025-12-24T14:45:14.828193"}, "trial_number": {"0": 1, "1": 2, "2": 3}}}